imgs/Paper-Arxiv-orange.svg
imgs/architecture.png
imgs/claude_desktop.jpg
imgs/dinggroup_out.png
imgs/goose.jpg
imgs/logo.png
imgs/witsy.jpg
src/xiyan_mcp_server/__init__.py
src/xiyan_mcp_server/__main__.py
src/xiyan_mcp_server/config_demo.yml
src/xiyan_mcp_server/database_env.py
src/xiyan_mcp_server/local_xiyan_server.py
src/xiyan_mcp_server/server.py
src/xiyan_mcp_server/utils/common_util.py
src/xiyan_mcp_server/utils/db_config.py
src/xiyan_mcp_server/utils/db_mschema.py
src/xiyan_mcp_server/utils/db_source.py
src/xiyan_mcp_server/utils/db_util.py
src/xiyan_mcp_server/utils/file_util.py
src/xiyan_mcp_server/utils/llm_util.py
src/xiyan_mcp_server/utils/logger_util.py
mseep_xiyan_mcp_server-0.1.4.dist-info/METADATA
mseep_xiyan_mcp_server-0.1.4.dist-info/WHEEL
mseep_xiyan_mcp_server-0.1.4.dist-info/entry_points.txt
mseep_xiyan_mcp_server-0.1.4.dist-info/licenses/LICENSE.txt
mseep_xiyan_mcp_server-0.1.4.dist-info/RECORD
