Metadata-Version: 2.4
Name: mseep-xiyan_mcp_server
Version: 0.1.4
Summary: A Model Context Protocol (MCP) server that utilizes XiyanSQL with databases. This server enables AI assistants to list tables, read data, and execute natural language queries
Author-email: Zhiling Luo <godot.lzl@alibaba-inc.com>
License-File: LICENSE.txt
Requires-Python: >=3.11
Requires-Dist: llama-index
Requires-Dist: mcp>=1.0.0
Requires-Dist: mysql-connector-python>=9.1.0
Requires-Dist: pymysql
Requires-Dist: sqlalchemy
